[
  {
    "notification_id": "1742857901007",
    "title": "Sekretariat",
    "message": "ITA23: Unterricht entfaellt morgen!",
    "sender": "Sekretariat",
    "time": "2025-03-24T23:11:41.007Z",
    "read": false,
    "avatar": "S"
  },
  {
    "notification_id": "1742858088893",
    "title": "Schuldirektor",
    "message": "Guten Morgen! Heute bitte die Schulversammlung und Ausflug nicht vergessen!",
    "sender": "Schuldirektor",
    "time": "2025-03-24T23:14:48.893Z",
    "read": false,
    "avatar": "S"
  }
]